LICENSE
MANIFEST.in
README.md
TODO
requirements.txt
setup.py
templates/default/base.html
templates/default/index.html
templates/default/page.html
templates/default/assets/style.css
test/test_builder.py
test/test_config_reader.py
wigiki/__init__.py
wigiki/__main__.py
wigiki/builder.py
wigiki/config.py
wigiki/core.py
wigiki/exceptions.py
wigiki/generator.py
wigiki.egg-info/PKG-INFO
wigiki.egg-info/SOURCES.txt
wigiki.egg-info/dependency_links.txt
wigiki.egg-info/entry_points.txt
wigiki.egg-info/requires.txt
wigiki.egg-info/top_level.txt