Metadata-Version: 1.1
Name: wigiki
Version: 0.6.4
Summary: A static site generator which uses Github's gists as pages
Home-page: https://github.com/tlatsas/wigiki
Author: Tasos Latsas
Author-email: tlatsas@gmx.com
License: MIT
Platform: UNKNOWN
Classifier: Development Status :: 4 - Beta
Classifier: Environment :: Console
Classifier: Intended Audience :: Developers
Classifier: Intended Audience :: End Users/Desktop
Classifier: Programming Language :: Python
Classifier: Programming Language :: Python :: 2.7
Classifier: Programming Language :: Python :: 3
Classifier: License :: OSI Approved :: MIT License
Classifier: Topic :: Internet
